{
  "__inputs": [
    {
      "name": "DS_PROMETHEUS",
      "label": "prometheus",
      "description": "",
      "type": "datasource",
      "pluginId": "prometheus",
      "pluginName": "Prometheus"
    }
  ],
  "__elements": {},
  "__requires": [
    {
      "type": "panel",
      "id": "bargauge",
      "name": "Bar gauge",
      "version": ""
    },
    {
      "type": "grafana",
      "id": "grafana",
      "name": "Grafana",
      "version": "9.1.6"
    },
    {
      "type": "panel",
      "id": "graph",
      "name": "Graph (old)",
      "version": ""
    },
    {
      "type": "datasource",
      "id": "prometheus",
      "name": "Prometheus",
      "version": "1.0.0"
    },
    {
      "type": "panel",
      "id": "stat",
      "name": "Stat",
      "version": ""
    },
    {
      "type": "panel",
      "id": "timeseries",
      "name": "Time series",
      "version": ""
    }
  ],
  "annotations": {
    "list": [
      {
        "builtIn": 1,
        "datasource": {
          "type": "datasource",
          "uid": "grafana"
        },
        "enable": true,
        "hide": true,
        "iconColor": "rgba(0, 211, 255, 1)",
        "name": "Annotations & Alerts",
        "target": {
          "limit": 100,
          "matchAny": false,
          "tags": [],
          "type": "dashboard"
        },
        "type": "dashboard"
      }
    ]
  },
  "description": "【中文版本】支持 Node Exporter v0.16及以上的版本，精简优化重要指标展示。包含：CPU 内存 磁盘 IO 网络 温度等监控指标。https://github.com/starsliao/Prometheus",
  "editable": true,
  "fiscalYearStartMonth": 0,
  "gnetId": 8919,
  "graphTooltip": 0,
  "id": null,
  "links": [],
  "liveNow": false,
  "panels": [
    {
      "collapsed": false,
      "datasource": {
        "type": "prometheus",
        "uid": "8dd2912a-9d69-4e8a-8c40-c4517dcb4e2e"
      },
      "gridPos": {
        "h": 1,
        "w": 24,
        "x": 0,
        "y": 0
      },
      "id": 177,
      "panels": [],
      "targets": [
        {
          "datasource": {
            "type": "prometheus",
            "uid": "8dd2912a-9d69-4e8a-8c40-c4517dcb4e2e"
          },
          "refId": "A"
        }
      ],
      "title": "Node 资源状态信息",
      "type": "row"
    },
    {
      "datasource": {
        "type": "prometheus",
        "uid": "${DS_PROMETHEUS}"
      },
      "fieldConfig": {
        "defaults": {
          "mappings": [],
          "thresholds": {
            "mode": "absolute",
            "steps": [
              {
                "color": "green",
                "value": null
              },
              {
                "color": "red",
                "value": 120
              }
            ]
          }
        },
        "overrides": []
      },
      "gridPos": {
        "h": 7,
        "w": 5,
        "x": 0,
        "y": 1
      },
      "id": 189,
      "options": {
        "colorMode": "value",
        "graphMode": "area",
        "justifyMode": "auto",
        "orientation": "auto",
        "reduceOptions": {
          "calcs": [
            "mean"
          ],
          "fields": "",
          "values": false
        },
        "text": {},
        "textMode": "auto"
      },
      "pluginVersion": "9.1.6",
      "targets": [
        {
          "datasource": {
            "type": "prometheus",
            "uid": "${DS_PROMETHEUS}"
          },
          "exemplar": false,
          "expr": "count(kube_pod_info{created_by_kind!~\"<none>|Job\",host_ip=~\"$host_ip\"}) by (node)",
          "format": "table",
          "instant": true,
          "interval": "",
          "legendFormat": "",
          "refId": "A"
        }
      ],
      "title": "pod 数量",
      "type": "stat"
    },
    {
      "aliasColors": {},
      "bars": false,
      "dashLength": 10,
      "dashes": false,
      "datasource": {
        "type": "prometheus",
        "uid": "${DS_PROMETHEUS}"
      },
      "fieldConfig": {
        "defaults": {
          "links": []
        },
        "overrides": []
      },
      "fill": 0,
      "fillGradient": 0,
      "gridPos": {
        "h": 7,
        "w": 6,
        "x": 5,
        "y": 1
      },
      "hiddenSeries": false,
      "id": 183,
      "legend": {
        "alignAsTable": true,
        "avg": false,
        "current": true,
        "max": false,
        "min": false,
        "rightSide": true,
        "show": true,
        "total": false,
        "values": true
      },
      "lines": true,
      "linewidth": 1,
      "nullPointMode": "null",
      "options": {
        "alertThreshold": true
      },
      "percentage": false,
      "pluginVersion": "9.1.6",
      "pointradius": 2,
      "points": false,
      "renderer": "flot",
      "seriesOverrides": [],
      "spaceLength": 10,
      "stack": false,
      "steppedLine": false,
      "targets": [
        {
          "datasource": {
            "type": "prometheus",
            "uid": "${DS_PROMETHEUS}"
          },
          "exemplar": true,
          "expr": "kube_node_status_capacity{resource=\"memory\",node=~\"$Node_name\"}",
          "hide": false,
          "interval": "",
          "legendFormat": "Total",
          "refId": "A"
        },
        {
          "datasource": {
            "type": "prometheus",
            "uid": "${DS_PROMETHEUS}"
          },
          "exemplar": true,
          "expr": "sum(kube_pod_container_resource_requests{resource=\"memory\",node=~\"$Node_name\"})",
          "hide": false,
          "interval": "",
          "legendFormat": "Request",
          "refId": "B"
        },
        {
          "datasource": {
            "type": "prometheus",
            "uid": "${DS_PROMETHEUS}"
          },
          "exemplar": true,
          "expr": "sum(kube_pod_container_resource_limits{resource=\"memory\",node=~\"$Node_name\"})",
          "hide": false,
          "interval": "",
          "legendFormat": "Limits",
          "refId": "C"
        }
      ],
      "thresholds": [],
      "timeRegions": [],
      "title": "Mem Usage By Node",
      "tooltip": {
        "shared": true,
        "sort": 0,
        "value_type": "individual"
      },
      "type": "graph",
      "xaxis": {
        "mode": "time",
        "show": true,
        "values": []
      },
      "yaxes": [
        {
          "$$hashKey": "object:1207",
          "format": "bytes",
          "logBase": 1,
          "show": true
        },
        {
          "$$hashKey": "object:1208",
          "format": "short",
          "logBase": 1,
          "show": true
        }
      ],
      "yaxis": {
        "align": false
      }
    },
    {
      "datasource": {
        "type": "prometheus",
        "uid": "${DS_PROMETHEUS}"
      },
      "fieldConfig": {
        "defaults": {
          "color": {
            "mode": "palette-classic"
          },
          "custom": {
            "axisCenteredZero": false,
            "axisColorMode": "text",
            "axisLabel": "",
            "axisPlacement": "auto",
            "barAlignment": 0,
            "drawStyle": "line",
            "fillOpacity": 0,
            "gradientMode": "none",
            "hideFrom": {
              "legend": false,
              "tooltip": false,
              "viz": false
            },
            "lineInterpolation": "linear",
            "lineWidth": 1,
            "pointSize": 5,
            "scaleDistribution": {
              "type": "linear"
            },
            "showPoints": "never",
            "spanNulls": true,
            "stacking": {
              "group": "A",
              "mode": "none"
            },
            "thresholdsStyle": {
              "mode": "off"
            }
          },
          "decimals": 1,
          "links": [],
          "mappings": [],
          "thresholds": {
            "mode": "absolute",
            "steps": [
              {
                "color": "green",
                "value": null
              },
              {
                "color": "red",
                "value": 80
              }
            ]
          },
          "unit": "short"
        },
        "overrides": []
      },
      "gridPos": {
        "h": 7,
        "w": 6,
        "x": 11,
        "y": 1
      },
      "id": 181,
      "options": {
        "legend": {
          "calcs": [
            "lastNotNull"
          ],
          "displayMode": "table",
          "placement": "right",
          "showLegend": true
        },
        "tooltip": {
          "mode": "multi",
          "sort": "none"
        }
      },
      "pluginVersion": "8.4.6",
      "targets": [
        {
          "datasource": {
            "type": "prometheus",
            "uid": "${DS_PROMETHEUS}"
          },
          "exemplar": true,
          "expr": "kube_node_status_capacity{resource=\"cpu\",node=~\"$Node_name\"}",
          "interval": "",
          "legendFormat": "CPU 总核数",
          "refId": "A"
        },
        {
          "datasource": {
            "type": "prometheus",
            "uid": "${DS_PROMETHEUS}"
          },
          "exemplar": true,
          "expr": "sum(kube_pod_container_resource_requests{resource=\"cpu\",node=~\"$Node_name\"})",
          "interval": "",
          "legendFormat": "Request",
          "refId": "B"
        },
        {
          "datasource": {
            "type": "prometheus",
            "uid": "${DS_PROMETHEUS}"
          },
          "exemplar": true,
          "expr": "sum(kube_pod_container_resource_limits{resource=\"cpu\",node=~\"$Node_name\"})",
          "interval": "",
          "legendFormat": "Limits",
          "refId": "C"
        }
      ],
      "title": "Cpu Usage By Node",
      "type": "timeseries"
    },
    {
      "datasource": {
        "type": "prometheus",
        "uid": "${DS_PROMETHEUS}"
      },
      "description": "",
      "fieldConfig": {
        "defaults": {
          "color": {
            "mode": "palette-classic"
          },
          "custom": {
            "axisCenteredZero": false,
            "axisColorMode": "text",
            "axisLabel": "",
            "axisPlacement": "auto",
            "barAlignment": 0,
            "drawStyle": "line",
            "fillOpacity": 0,
            "gradientMode": "none",
            "hideFrom": {
              "legend": false,
              "tooltip": false,
              "viz": false
            },
            "lineInterpolation": "linear",
            "lineWidth": 2,
            "pointSize": 5,
            "scaleDistribution": {
              "type": "linear"
            },
            "showPoints": "never",
            "spanNulls": true,
            "stacking": {
              "group": "A",
              "mode": "none"
            },
            "thresholdsStyle": {
              "mode": "off"
            }
          },
          "decimals": 1,
          "links": [],
          "mappings": [],
          "thresholds": {
            "mode": "absolute",
            "steps": [
              {
                "color": "green",
                "value": null
              },
              {
                "color": "red",
                "value": 80
              }
            ]
          },
          "unit": "percentunit"
        },
        "overrides": [
          {
            "matcher": {
              "id": "byName",
              "options": "192.168.200.241:9100_Total"
            },
            "properties": [
              {
                "id": "color",
                "value": {
                  "fixedColor": "dark-red",
                  "mode": "fixed"
                }
              }
            ]
          },
          {
            "matcher": {
              "id": "byName",
              "options": "Idle - Waiting for something to happen"
            },
            "properties": [
              {
                "id": "color",
                "value": {
                  "fixedColor": "#052B51",
                  "mode": "fixed"
                }
              }
            ]
          },
          {
            "matcher": {
              "id": "byName",
              "options": "guest"
            },
            "properties": [
              {
                "id": "color",
                "value": {
                  "fixedColor": "#9AC48A",
                  "mode": "fixed"
                }
              }
            ]
          },
          {
            "matcher": {
              "id": "byName",
              "options": "idle"
            },
            "properties": [
              {
                "id": "color",
                "value": {
                  "fixedColor": "#052B51",
                  "mode": "fixed"
                }
              }
            ]
          },
          {
            "matcher": {
              "id": "byName",
              "options": "iowait"
            },
            "properties": [
              {
                "id": "color",
                "value": {
                  "fixedColor": "#EAB839",
                  "mode": "fixed"
                }
              }
            ]
          },
          {
            "matcher": {
              "id": "byName",
              "options": "irq"
            },
            "properties": [
              {
                "id": "color",
                "value": {
                  "fixedColor": "#BF1B00",
                  "mode": "fixed"
                }
              }
            ]
          },
          {
            "matcher": {
              "id": "byName",
              "options": "nice"
            },
            "properties": [
              {
                "id": "color",
                "value": {
                  "fixedColor": "#C15C17",
                  "mode": "fixed"
                }
              }
            ]
          },
          {
            "matcher": {
              "id": "byName",
              "options": "sdb_每秒I/O操作%"
            },
            "properties": [
              {
                "id": "color",
                "value": {
                  "fixedColor": "#d683ce",
                  "mode": "fixed"
                }
              }
            ]
          },
          {
            "matcher": {
              "id": "byName",
              "options": "softirq"
            },
            "properties": [
              {
                "id": "color",
                "value": {
                  "fixedColor": "#E24D42",
                  "mode": "fixed"
                }
              }
            ]
          },
          {
            "matcher": {
              "id": "byName",
              "options": "steal"
            },
            "properties": [
              {
                "id": "color",
                "value": {
                  "fixedColor": "#FCE2DE",
                  "mode": "fixed"
                }
              }
            ]
          },
          {
            "matcher": {
              "id": "byName",
              "options": "system"
            },
            "properties": [
              {
                "id": "color",
                "value": {
                  "fixedColor": "#508642",
                  "mode": "fixed"
                }
              }
            ]
          },
          {
            "matcher": {
              "id": "byName",
              "options": "user"
            },
            "properties": [
              {
                "id": "color",
                "value": {
                  "fixedColor": "#5195CE",
                  "mode": "fixed"
                }
              }
            ]
          },
          {
            "matcher": {
              "id": "byName",
              "options": "磁盘花费在I/O操作占比"
            },
            "properties": [
              {
                "id": "color",
                "value": {
                  "fixedColor": "#ba43a9",
                  "mode": "fixed"
                }
              }
            ]
          },
          {
            "matcher": {
              "id": "byRegexp",
              "options": "/.*_Total/"
            },
            "properties": [
              {
                "id": "color",
                "value": {
                  "fixedColor": "#C4162A",
                  "mode": "fixed"
                }
              },
              {
                "id": "custom.fillOpacity",
                "value": 0
              }
            ]
          }
        ]
      },
      "gridPos": {
        "h": 7,
        "w": 7,
        "x": 17,
        "y": 1
      },
      "id": 7,
      "links": [],
      "options": {
        "legend": {
          "calcs": [
            "mean",
            "lastNotNull",
            "max"
          ],
          "displayMode": "table",
          "placement": "bottom",
          "showLegend": true
        },
        "tooltip": {
          "mode": "multi",
          "sort": "desc"
        }
      },
      "pluginVersion": "8.4.6",
      "targets": [
        {
          "datasource": {
            "type": "prometheus",
            "uid": "${DS_PROMETHEUS}"
          },
          "exemplar": true,
          "expr": "avg(irate(node_cpu_seconds_total{instance=~\"$Node_name\",mode=\"system\"}[5m])) by (instance)",
          "format": "time_series",
          "hide": false,
          "instant": false,
          "interval": "",
          "intervalFactor": 1,
          "legendFormat": "$host_ip-System",
          "refId": "A",
          "step": 20
        },
        {
          "datasource": {
            "type": "prometheus",
            "uid": "${DS_PROMETHEUS}"
          },
          "exemplar": true,
          "expr": "avg(irate(node_cpu_seconds_total{instance=~\"$Node_name\",mode=\"user\"}[5m])) by (instance)",
          "format": "time_series",
          "hide": false,
          "interval": "",
          "intervalFactor": 1,
          "legendFormat": "$host_ip-User",
          "refId": "B",
          "step": 240
        },
        {
          "datasource": {
            "type": "prometheus",
            "uid": "${DS_PROMETHEUS}"
          },
          "exemplar": true,
          "expr": "avg(irate(node_cpu_seconds_total{instance=~\"$Node_name\",mode=\"iowait\"}[5m])) by (instance)",
          "format": "time_series",
          "hide": false,
          "instant": false,
          "interval": "",
          "intervalFactor": 1,
          "legendFormat": "$host_ip-Iowait",
          "refId": "D",
          "step": 240
        },
        {
          "datasource": {
            "type": "prometheus",
            "uid": "${DS_PROMETHEUS}"
          },
          "exemplar": true,
          "expr": "1 - avg(irate(node_cpu_seconds_total{instance=~\"$Node_name\",mode=\"idle\"}[5m])) by (instance)",
          "format": "time_series",
          "hide": false,
          "interval": "",
          "intervalFactor": 1,
          "legendFormat": "$host_ip-Used",
          "refId": "F",
          "step": 240
        }
      ],
      "title": "CPU使用率",
      "type": "timeseries"
    },
    {
      "datasource": {
        "type": "prometheus",
        "uid": "${DS_PROMETHEUS}"
      },
      "fieldConfig": {
        "defaults": {
          "color": {
            "mode": "continuous-GrYlRd"
          },
          "custom": {
            "axisCenteredZero": false,
            "axisColorMode": "text",
            "axisLabel": "",
            "axisPlacement": "auto",
            "barAlignment": 0,
            "drawStyle": "line",
            "fillOpacity": 5,
            "gradientMode": "none",
            "hideFrom": {
              "legend": false,
              "tooltip": false,
              "viz": false
            },
            "lineInterpolation": "linear",
            "lineWidth": 1,
            "pointSize": 1,
            "scaleDistribution": {
              "type": "linear"
            },
            "showPoints": "auto",
            "spanNulls": false,
            "stacking": {
              "group": "A",
              "mode": "none"
            },
            "thresholdsStyle": {
              "mode": "off"
            }
          },
          "mappings": [],
          "thresholds": {
            "mode": "absolute",
            "steps": [
              {
                "color": "green",
                "value": null
              },
              {
                "color": "red",
                "value": 80
              }
            ]
          },
          "unit": "bytes"
        },
        "overrides": []
      },
      "gridPos": {
        "h": 7,
        "w": 8,
        "x": 0,
        "y": 8
      },
      "id": 230,
      "options": {
        "legend": {
          "calcs": [
            "lastNotNull"
          ],
          "displayMode": "table",
          "placement": "bottom",
          "showLegend": true
        },
        "tooltip": {
          "mode": "single",
          "sort": "none"
        }
      },
      "pluginVersion": "8.4.6",
      "targets": [
        {
          "datasource": {
            "type": "prometheus",
            "uid": "${DS_PROMETHEUS}"
          },
          "exemplar": true,
          "expr": "node_filesystem_size_bytes{device=~\"^/dev/.*\",mountpoint!~\"^/boot.*\",instance=~\"$Node_name\"}",
          "interval": "",
          "legendFormat": "总大小：{{device}}-{{mountpoint}}",
          "refId": "A"
        },
        {
          "datasource": {
            "type": "prometheus",
            "uid": "${DS_PROMETHEUS}"
          },
          "exemplar": true,
          "expr": "node_filesystem_free_bytes{device=~\"^/dev/.*\",mountpoint!~\"^/boot.*\",instance=~\"$Node_name\"}",
          "hide": false,
          "interval": "",
          "legendFormat": "未使用：{{device}}-{{mountpoint}}",
          "refId": "B"
        }
      ],
      "title": "Disk Usage(G)",
      "type": "timeseries"
    },
    {
      "datasource": {
        "type": "prometheus",
        "uid": "${DS_PROMETHEUS}"
      },
      "fieldConfig": {
        "defaults": {
          "color": {
            "mode": "palette-classic"
          },
          "custom": {
            "axisCenteredZero": false,
            "axisColorMode": "text",
            "axisLabel": "",
            "axisPlacement": "auto",
            "barAlignment": 0,
            "drawStyle": "line",
            "fillOpacity": 30,
            "gradientMode": "opacity",
            "hideFrom": {
              "legend": false,
              "tooltip": false,
              "viz": false
            },
            "lineInterpolation": "linear",
            "lineWidth": 2,
            "pointSize": 5,
            "scaleDistribution": {
              "type": "linear"
            },
            "showPoints": "never",
            "spanNulls": true,
            "stacking": {
              "group": "A",
              "mode": "none"
            },
            "thresholdsStyle": {
              "mode": "off"
            }
          },
          "decimals": 1,
          "links": [],
          "mappings": [],
          "thresholds": {
            "mode": "absolute",
            "steps": [
              {
                "color": "green",
                "value": null
              },
              {
                "color": "red",
                "value": 80
              }
            ]
          },
          "unit": "percentunit"
        },
        "overrides": [
          {
            "matcher": {
              "id": "byRegexp",
              "options": "/Inodes.*/"
            },
            "properties": [
              {
                "id": "max",
                "value": 1
              }
            ]
          }
        ]
      },
      "gridPos": {
        "h": 7,
        "w": 8,
        "x": 8,
        "y": 8
      },
      "id": 174,
      "links": [],
      "options": {
        "legend": {
          "calcs": [
            "lastNotNull"
          ],
          "displayMode": "table",
          "placement": "bottom",
          "showLegend": true
        },
        "tooltip": {
          "mode": "multi",
          "sort": "desc"
        }
      },
      "pluginVersion": "8.4.6",
      "targets": [
        {
          "datasource": {
            "type": "prometheus",
            "uid": "${DS_PROMETHEUS}"
          },
          "exemplar": true,
          "expr": "1-(node_filesystem_avail_bytes{instance=~\"$Node_name\",device=~\"^/dev.*\",fstype=~\"ext4|xfs\",mountpoint!=\"/boot\"} / node_filesystem_size_bytes{instance=~\"$Node_name\",fstype=~\"ext4|xfs\",mountpoint!=\"/boot\"})",
          "format": "time_series",
          "instant": false,
          "interval": "",
          "intervalFactor": 1,
          "legendFormat": "disk_used——{{device}}-{{mountpoint}}",
          "refId": "A"
        },
        {
          "datasource": {
            "type": "prometheus",
            "uid": "${DS_PROMETHEUS}"
          },
          "exemplar": true,
          "expr": "1-(node_filesystem_files_free{instance=~\"$Node_name\",device=~\"^/dev.*\",fstype=~\"ext4|xfs\",mountpoint!=\"/boot\"} / node_filesystem_files{instance=~\"$Node_name\",fstype=~\"ext4|xfs\",mountpoint!=\"/boot\"})",
          "hide": false,
          "interval": "",
          "legendFormat": "Inodes_free：{{device}}-{{mountpoint}}",
          "refId": "B"
        }
      ],
      "title": "分时磁盘使用率",
      "type": "timeseries"
    },
    {
      "aliasColors": {
        "192.168.10.227:9100_em1_in下载": "super-light-green",
        "192.168.10.227:9100_em1_out上传": "dark-blue"
      },
      "bars": false,
      "dashLength": 10,
      "dashes": false,
      "datasource": {
        "type": "prometheus",
        "uid": "${DS_PROMETHEUS}"
      },
      "fieldConfig": {
        "defaults": {
          "links": []
        },
        "overrides": []
      },
      "fill": 0,
      "fillGradient": 3,
      "gridPos": {
        "h": 7,
        "w": 8,
        "x": 16,
        "y": 8
      },
      "height": "300",
      "hiddenSeries": false,
      "id": 157,
      "legend": {
        "alignAsTable": true,
        "avg": false,
        "current": true,
        "hideEmpty": true,
        "hideZero": true,
        "max": true,
        "min": false,
        "rightSide": false,
        "show": true,
        "sort": "current",
        "sortDesc": true,
        "total": false,
        "values": true
      },
      "lines": true,
      "linewidth": 2,
      "links": [],
      "nullPointMode": "null",
      "options": {
        "alertThreshold": true
      },
      "percentage": false,
      "pluginVersion": "9.1.6",
      "pointradius": 2,
      "points": false,
      "renderer": "flot",
      "seriesOverrides": [
        {
          "$$hashKey": "object:2075",
          "alias": "/.*_out上传$/",
          "transform": "negative-Y"
        }
      ],
      "spaceLength": 10,
      "stack": false,
      "steppedLine": false,
      "targets": [
        {
          "datasource": {
            "type": "prometheus",
            "uid": "${DS_PROMETHEUS}"
          },
          "exemplar": true,
          "expr": "irate(node_network_receive_bytes_total{instance=~\"$Node_name\",device!~'tap.*|veth.*|br.*|docker.*|virbr*|lo*'}[5m])*8",
          "format": "time_series",
          "interval": "",
          "intervalFactor": 1,
          "legendFormat": "{{host_ip}}_{{device}}_in  接收",
          "refId": "A",
          "step": 4
        },
        {
          "datasource": {
            "type": "prometheus",
            "uid": "${DS_PROMETHEUS}"
          },
          "exemplar": true,
          "expr": "-irate(node_network_transmit_bytes_total{instance=~\"$Node_name\",device!~'tap.*|veth.*|br.*|docker.*|virbr*|lo*'}[5m])*8",
          "format": "time_series",
          "interval": "",
          "intervalFactor": 1,
          "legendFormat": "{{host_ip}}_{{device}}_out 上传",
          "refId": "B",
          "step": 4
        }
      ],
      "thresholds": [],
      "timeRegions": [],
      "title": "网络流量",
      "tooltip": {
        "shared": true,
        "sort": 2,
        "value_type": "individual"
      },
      "type": "graph",
      "xaxis": {
        "mode": "time",
        "show": true,
        "values": []
      },
      "yaxes": [
        {
          "$$hashKey": "object:2082",
          "format": "bps",
          "label": "上传（-）/下载（+）",
          "logBase": 1,
          "show": true
        },
        {
          "$$hashKey": "object:2083",
          "format": "short",
          "logBase": 1,
          "show": false
        }
      ],
      "yaxis": {
        "align": false
      }
    },
    {
      "aliasColors": {
        "15分钟": "#6ED0E0",
        "1分钟": "#BF1B00",
        "5分钟": "#CCA300"
      },
      "bars": false,
      "dashLength": 10,
      "dashes": false,
      "datasource": {
        "type": "prometheus",
        "uid": "${DS_PROMETHEUS}"
      },
      "editable": true,
      "error": false,
      "fieldConfig": {
        "defaults": {
          "links": []
        },
        "overrides": []
      },
      "fill": 1,
      "fillGradient": 1,
      "grid": {},
      "gridPos": {
        "h": 7,
        "w": 8,
        "x": 0,
        "y": 15
      },
      "height": "300",
      "hiddenSeries": false,
      "id": 13,
      "legend": {
        "alignAsTable": true,
        "avg": true,
        "current": true,
        "max": true,
        "min": false,
        "rightSide": false,
        "show": true,
        "total": false,
        "values": true
      },
      "lines": true,
      "linewidth": 2,
      "links": [],
      "maxPerRow": 6,
      "nullPointMode": "null as zero",
      "options": {
        "alertThreshold": true
      },
      "percentage": false,
      "pluginVersion": "9.1.6",
      "pointradius": 5,
      "points": false,
      "renderer": "flot",
      "seriesOverrides": [],
      "spaceLength": 10,
      "stack": false,
      "steppedLine": false,
      "targets": [
        {
          "datasource": {
            "type": "prometheus",
            "uid": "${DS_PROMETHEUS}"
          },
          "exemplar": true,
          "expr": "node_load1{instance=~\"$Node_name\"}",
          "format": "time_series",
          "instant": false,
          "interval": "",
          "intervalFactor": 1,
          "legendFormat": "{{host_ip}}_1m",
          "metric": "",
          "refId": "A",
          "step": 20,
          "target": ""
        },
        {
          "datasource": {
            "type": "prometheus",
            "uid": "${DS_PROMETHEUS}"
          },
          "exemplar": true,
          "expr": "node_load5{instance=~\"$Node_name\"}",
          "format": "time_series",
          "instant": false,
          "interval": "",
          "intervalFactor": 1,
          "legendFormat": "{{host_ip}}_5m",
          "refId": "B",
          "step": 20
        },
        {
          "datasource": {
            "type": "prometheus",
            "uid": "${DS_PROMETHEUS}"
          },
          "exemplar": true,
          "expr": "node_load15{instance=~\"$Node_name\"}",
          "format": "time_series",
          "instant": false,
          "interval": "",
          "intervalFactor": 1,
          "legendFormat": "{{host_ip}}_15m",
          "refId": "C",
          "step": 20
        }
      ],
      "thresholds": [],
      "timeRegions": [],
      "title": "系统平均负载",
      "tooltip": {
        "msResolution": false,
        "shared": true,
        "sort": 2,
        "value_type": "cumulative"
      },
      "type": "graph",
      "xaxis": {
        "mode": "time",
        "show": true,
        "values": []
      },
      "yaxes": [
        {
          "$$hashKey": "object:2156",
          "format": "short",
          "logBase": 1,
          "show": true
        },
        {
          "$$hashKey": "object:2157",
          "format": "short",
          "logBase": 1,
          "show": true
        }
      ],
      "yaxis": {
        "align": false
      }
    },
    {
      "datasource": {
        "type": "prometheus",
        "uid": "${DS_PROMETHEUS}"
      },
      "description": "",
      "fieldConfig": {
        "defaults": {
          "color": {
            "mode": "palette-classic"
          },
          "custom": {
            "axisCenteredZero": false,
            "axisColorMode": "text",
            "axisLabel": "",
            "axisPlacement": "auto",
            "barAlignment": 0,
            "drawStyle": "line",
            "fillOpacity": 10,
            "gradientMode": "opacity",
            "hideFrom": {
              "legend": false,
              "tooltip": false,
              "viz": false
            },
            "lineInterpolation": "linear",
            "lineWidth": 2,
            "pointSize": 1,
            "scaleDistribution": {
              "type": "linear"
            },
            "showPoints": "never",
            "spanNulls": true,
            "stacking": {
              "group": "A",
              "mode": "none"
            },
            "thresholdsStyle": {
              "mode": "off"
            }
          },
          "links": [],
          "mappings": [],
          "thresholds": {
            "mode": "absolute",
            "steps": [
              {
                "color": "green",
                "value": null
              },
              {
                "color": "red",
                "value": 80
              }
            ]
          },
          "unit": "short"
        },
        "overrides": []
      },
      "gridPos": {
        "h": 7,
        "w": 8,
        "x": 8,
        "y": 15
      },
      "hideTimeOverride": false,
      "id": 16,
      "links": [],
      "options": {
        "legend": {
          "calcs": [
            "lastNotNull",
            "max"
          ],
          "displayMode": "table",
          "placement": "bottom",
          "showLegend": true
        },
        "tooltip": {
          "mode": "multi",
          "sort": "desc"
        }
      },
      "pluginVersion": "8.4.6",
      "targets": [
        {
          "datasource": {
            "type": "prometheus",
            "uid": "${DS_PROMETHEUS}"
          },
          "exemplar": true,
          "expr": "node_filefd_allocated{instance=~\"$Node_name\"}",
          "format": "time_series",
          "instant": false,
          "interval": "",
          "intervalFactor": 5,
          "legendFormat": "当前进程已经打开的文件描述符数量",
          "refId": "B"
        },
        {
          "datasource": {
            "type": "prometheus",
            "uid": "${DS_PROMETHEUS}"
          },
          "exemplar": true,
          "expr": "irate(node_context_switches_total{instance=~\"$Node_name\"}[5m])",
          "interval": "",
          "intervalFactor": 5,
          "legendFormat": "每秒上下文切换次数",
          "refId": "A"
        },
        {
          "datasource": {
            "type": "prometheus",
            "uid": "${DS_PROMETHEUS}"
          },
          "exemplar": true,
          "expr": "node_filefd_maximum{instance=~\"$Node_name\"}",
          "hide": false,
          "interval": "",
          "legendFormat": "单个进程可以打开的最大文件描述符数量",
          "refId": "C"
        }
      ],
      "title": "打开的文件描述符(左 )/每秒上下文切换次数(右)",
      "type": "timeseries"
    },
    {
      "aliasColors": {
        "192.168.200.241:9100_总内存": "dark-red",
        "内存_Avaliable": "#6ED0E0",
        "内存_Cached": "#EF843C",
        "内存_Free": "#629E51",
        "内存_Total": "#6d1f62",
        "内存_Used": "#eab839",
        "可用": "#9ac48a",
        "总内存": "#bf1b00"
      },
      "bars": false,
      "dashLength": 10,
      "dashes": false,
      "datasource": {
        "type": "prometheus",
        "uid": "${DS_PROMETHEUS}"
      },
      "decimals": 2,
      "fieldConfig": {
        "defaults": {
          "links": []
        },
        "overrides": []
      },
      "fill": 0,
      "fillGradient": 0,
      "gridPos": {
        "h": 7,
        "w": 8,
        "x": 16,
        "y": 15
      },
      "height": "300",
      "hiddenSeries": false,
      "id": 236,
      "legend": {
        "alignAsTable": true,
        "avg": false,
        "current": true,
        "max": false,
        "min": false,
        "rightSide": false,
        "show": true,
        "sort": "current",
        "sortDesc": true,
        "total": false,
        "values": true
      },
      "lines": true,
      "linewidth": 2,
      "links": [],
      "nullPointMode": "null",
      "options": {
        "alertThreshold": true
      },
      "percentage": false,
      "pluginVersion": "9.1.6",
      "pointradius": 5,
      "points": false,
      "renderer": "flot",
      "seriesOverrides": [
        {
          "$$hashKey": "object:2561",
          "alias": "/.*_总内存/",
          "color": "#C4162A",
          "fill": 0
        }
      ],
      "spaceLength": 10,
      "stack": false,
      "steppedLine": false,
      "targets": [
        {
          "datasource": {
            "type": "prometheus",
            "uid": "${DS_PROMETHEUS}"
          },
          "exemplar": true,
          "expr": "node_memory_MemTotal_bytes{instance=~\"$Node_name\"}",
          "format": "time_series",
          "hide": false,
          "instant": false,
          "interval": "",
          "intervalFactor": 1,
          "legendFormat": "$host_ip-总内存",
          "refId": "A",
          "step": 4
        },
        {
          "datasource": {
            "type": "prometheus",
            "uid": "${DS_PROMETHEUS}"
          },
          "exemplar": true,
          "expr": "node_memory_MemTotal_bytes{instance=~\"$Node_name\"} - node_memory_MemAvailable_bytes{instance=~\"$Node\"}",
          "format": "time_series",
          "hide": false,
          "interval": "",
          "intervalFactor": 1,
          "legendFormat": "$host_ip-已用",
          "refId": "B",
          "step": 4
        },
        {
          "datasource": {
            "type": "prometheus",
            "uid": "${DS_PROMETHEUS}"
          },
          "exemplar": true,
          "expr": "node_memory_MemAvailable_bytes{instance=~\"$Node_name\"}",
          "format": "time_series",
          "hide": false,
          "interval": "",
          "intervalFactor": 1,
          "legendFormat": "$host_ip-可用",
          "refId": "F",
          "step": 4
        },
        {
          "datasource": {
            "type": "prometheus",
            "uid": "${DS_PROMETHEUS}"
          },
          "exemplar": true,
          "expr": "node_memory_Buffers_bytes{instance=~\"$Node_name\"}",
          "format": "time_series",
          "hide": false,
          "interval": "",
          "intervalFactor": 1,
          "legendFormat": "$host_ip-Buffers",
          "refId": "D",
          "step": 4
        },
        {
          "datasource": {
            "type": "prometheus",
            "uid": "${DS_PROMETHEUS}"
          },
          "exemplar": true,
          "expr": "node_memory_MemFree_bytes{instance=~\"$Node_name\"}",
          "format": "time_series",
          "hide": false,
          "interval": "",
          "intervalFactor": 1,
          "legendFormat": "$host_ip-Free",
          "refId": "C",
          "step": 4
        },
        {
          "datasource": {
            "type": "prometheus",
            "uid": "${DS_PROMETHEUS}"
          },
          "exemplar": true,
          "expr": "node_memory_Cached_bytes{instance=~\"$Node_name\"}",
          "format": "time_series",
          "hide": false,
          "interval": "",
          "intervalFactor": 1,
          "legendFormat": "$host_ip-Cached",
          "refId": "E",
          "step": 4
        }
      ],
      "thresholds": [],
      "timeRegions": [],
      "title": "内存信息",
      "tooltip": {
        "shared": true,
        "sort": 2,
        "value_type": "individual"
      },
      "type": "graph",
      "xaxis": {
        "mode": "time",
        "show": true,
        "values": []
      },
      "yaxes": [
        {
          "$$hashKey": "object:2570",
          "format": "bytes",
          "logBase": 1,
          "min": "0",
          "show": true
        },
        {
          "$$hashKey": "object:2571",
          "format": "short",
          "logBase": 1,
          "show": true
        }
      ],
      "yaxis": {
        "align": false
      }
    },
    {
      "datasource": {
        "type": "prometheus",
        "uid": "${DS_PROMETHEUS}"
      },
      "description": "Reads completed: 每个磁盘分区每秒读完成次数\n\nWrites completed: 每个磁盘分区每秒写完成次数\n\nIO now 每个磁盘分区每秒正在处理的输入/输出请求数",
      "fieldConfig": {
        "defaults": {
          "color": {
            "mode": "palette-classic"
          },
          "custom": {
            "axisCenteredZero": false,
            "axisColorMode": "text",
            "axisLabel": "读取（-）/写入（+）I/O ops/sec",
            "axisPlacement": "auto",
            "barAlignment": 0,
            "drawStyle": "line",
            "fillOpacity": 10,
            "gradientMode": "opacity",
            "hideFrom": {
              "legend": false,
              "tooltip": false,
              "viz": false
            },
            "lineInterpolation": "linear",
            "lineWidth": 2,
            "pointSize": 5,
            "scaleDistribution": {
              "type": "linear"
            },
            "showPoints": "never",
            "spanNulls": true,
            "stacking": {
              "group": "A",
              "mode": "none"
            },
            "thresholdsStyle": {
              "mode": "off"
            }
          },
          "links": [],
          "mappings": [],
          "thresholds": {
            "mode": "absolute",
            "steps": [
              {
                "color": "green",
                "value": null
              },
              {
                "color": "red",
                "value": 80
              }
            ]
          },
          "unit": "iops"
        },
        "overrides": [
          {
            "matcher": {
              "id": "byName",
              "options": "vda_write"
            },
            "properties": [
              {
                "id": "color",
                "value": {
                  "fixedColor": "#6ED0E0",
                  "mode": "fixed"
                }
              }
            ]
          },
          {
            "matcher": {
              "id": "byRegexp",
              "options": "/.*_读取$/"
            },
            "properties": [
              {
                "id": "custom.transform",
                "value": "negative-Y"
              }
            ]
          }
        ]
      },
      "gridPos": {
        "h": 7,
        "w": 8,
        "x": 0,
        "y": 22
      },
      "id": 161,
      "links": [],
      "options": {
        "legend": {
          "calcs": [
            "mean",
            "lastNotNull",
            "max"
          ],
          "displayMode": "table",
          "placement": "bottom",
          "showLegend": true
        },
        "tooltip": {
          "mode": "multi",
          "sort": "desc"
        }
      },
      "pluginVersion": "8.4.6",
      "targets": [
        {
          "datasource": {
            "type": "prometheus",
            "uid": "${DS_PROMETHEUS}"
          },
          "exemplar": true,
          "expr": "irate(node_disk_reads_completed_total{instance=~\"$Node_name\"}[5m])",
          "format": "time_series",
          "hide": false,
          "interval": "",
          "intervalFactor": 1,
          "legendFormat": "$host_ip-{{device}}_读取",
          "refId": "A",
          "step": 10
        },
        {
          "datasource": {
            "type": "prometheus",
            "uid": "${DS_PROMETHEUS}"
          },
          "exemplar": true,
          "expr": "irate(node_disk_writes_completed_total{instance=~\"$Node_name\"}[5m])",
          "format": "time_series",
          "hide": false,
          "interval": "",
          "intervalFactor": 1,
          "legendFormat": "$host_ip-{{device}}_写入",
          "refId": "B",
          "step": 10
        }
      ],
      "title": "磁盘读写速率（IOPS）5m",
      "type": "timeseries"
    },
    {
      "aliasColors": {
        "192.168.200.241:9100_TCP_alloc": "semi-dark-blue",
        "TCP": "#6ED0E0"
      },
      "bars": false,
      "dashLength": 10,
      "dashes": false,
      "datasource": {
        "type": "prometheus",
        "uid": "${DS_PROMETHEUS}"
      },
      "description": "Sockets_used - 已使用的所有协议套接字总量\n\nCurrEstab - 当前状态为 ESTABLISHED 或 CLOSE-WAIT 的 TCP 连接数\n\nTCP_alloc - 已分配（已建立、已申请到sk_buff）的TCP套接字数量\n\nTCP_tw - 等待关闭的TCP连接数\n\nUDP_inuse - 正在使用的 UDP 套接字数量",
      "fieldConfig": {
        "defaults": {
          "links": []
        },
        "overrides": []
      },
      "fill": 0,
      "fillGradient": 0,
      "gridPos": {
        "h": 7,
        "w": 8,
        "x": 8,
        "y": 22
      },
      "height": "300",
      "hiddenSeries": false,
      "id": 158,
      "interval": "",
      "legend": {
        "alignAsTable": true,
        "avg": true,
        "current": true,
        "hideEmpty": true,
        "hideZero": true,
        "max": true,
        "min": false,
        "rightSide": false,
        "show": true,
        "sort": "current",
        "sortDesc": true,
        "total": false,
        "values": true
      },
      "lines": true,
      "linewidth": 2,
      "links": [],
      "nullPointMode": "null",
      "options": {
        "alertThreshold": true
      },
      "percentage": false,
      "pluginVersion": "9.1.6",
      "pointradius": 5,
      "points": false,
      "renderer": "flot",
      "seriesOverrides": [
        {
          "$$hashKey": "object:135",
          "alias": "/.*_Sockets_used/",
          "color": "#C4162A",
          "fill": 0
        }
      ],
      "spaceLength": 10,
      "stack": false,
      "steppedLine": false,
      "targets": [
        {
          "datasource": {
            "type": "prometheus",
            "uid": "${DS_PROMETHEUS}"
          },
          "exemplar": true,
          "expr": "node_netstat_Tcp_CurrEstab{instance=~\"$Node_name\"}",
          "format": "time_series",
          "hide": false,
          "instant": false,
          "interval": "",
          "intervalFactor": 1,
          "legendFormat": "$host_ip-CurrEstab",
          "refId": "A",
          "step": 20
        },
        {
          "datasource": {
            "type": "prometheus",
            "uid": "${DS_PROMETHEUS}"
          },
          "exemplar": true,
          "expr": "node_sockstat_TCP_tw{instance=~\"$Node_name\"}",
          "format": "time_series",
          "interval": "",
          "intervalFactor": 1,
          "legendFormat": "$host_ip-TCP_tw",
          "refId": "D"
        },
        {
          "datasource": {
            "type": "prometheus",
            "uid": "${DS_PROMETHEUS}"
          },
          "exemplar": true,
          "expr": "node_sockstat_sockets_used{instance=~\"$Node_name\"}",
          "interval": "",
          "legendFormat": "$host_ip-Sockets_used",
          "refId": "B"
        },
        {
          "datasource": {
            "type": "prometheus",
            "uid": "${DS_PROMETHEUS}"
          },
          "exemplar": true,
          "expr": "node_sockstat_UDP_inuse{instance=~\"$Node_name\"}",
          "interval": "",
          "legendFormat": "$host_ip-UDP_inuse",
          "refId": "C"
        },
        {
          "datasource": {
            "type": "prometheus",
            "uid": "${DS_PROMETHEUS}"
          },
          "exemplar": true,
          "expr": "node_sockstat_TCP_alloc{instance=~\"$Node_name\"}",
          "interval": "",
          "legendFormat": "$host_ip-TCP_alloc",
          "refId": "E"
        }
      ],
      "thresholds": [],
      "timeRegions": [],
      "title": "网络连接信息",
      "tooltip": {
        "shared": true,
        "sort": 2,
        "value_type": "individual"
      },
      "type": "graph",
      "xaxis": {
        "mode": "time",
        "show": true,
        "values": []
      },
      "yaxes": [
        {
          "$$hashKey": "object:144",
          "format": "short",
          "logBase": 1,
          "show": true
        },
        {
          "$$hashKey": "object:145",
          "format": "short",
          "logBase": 1,
          "show": true
        }
      ],
      "yaxis": {
        "align": false
      }
    },
    {
      "datasource": {
        "type": "prometheus",
        "uid": "${DS_PROMETHEUS}"
      },
      "fieldConfig": {
        "defaults": {
          "color": {
            "mode": "palette-classic"
          },
          "custom": {
            "axisCenteredZero": false,
            "axisColorMode": "text",
            "axisLabel": "",
            "axisPlacement": "auto",
            "barAlignment": 0,
            "drawStyle": "line",
            "fillOpacity": 0,
            "gradientMode": "none",
            "hideFrom": {
              "legend": false,
              "tooltip": false,
              "viz": false
            },
            "lineInterpolation": "linear",
            "lineWidth": 1,
            "pointSize": 5,
            "scaleDistribution": {
              "type": "linear"
            },
            "showPoints": "auto",
            "spanNulls": false,
            "stacking": {
              "group": "A",
              "mode": "none"
            },
            "thresholdsStyle": {
              "mode": "off"
            }
          },
          "mappings": [],
          "thresholds": {
            "mode": "absolute",
            "steps": [
              {
                "color": "green",
                "value": null
              },
              {
                "color": "red",
                "value": 80
              }
            ]
          }
        },
        "overrides": []
      },
      "gridPos": {
        "h": 7,
        "w": 8,
        "x": 16,
        "y": 22
      },
      "id": 232,
      "options": {
        "legend": {
          "calcs": [
            "lastNotNull"
          ],
          "displayMode": "table",
          "placement": "bottom",
          "showLegend": true
        },
        "tooltip": {
          "mode": "single",
          "sort": "none"
        }
      },
      "targets": [
        {
          "datasource": {
            "type": "prometheus",
            "uid": "${DS_PROMETHEUS}"
          },
          "editorMode": "code",
          "exemplar": true,
          "expr": "node_tcp_connection_states{host_ip=~\"$host_ip\",state!~\"^tx_.*|^^rx_.*\"}",
          "interval": "",
          "legendFormat": "{{state}}",
          "range": true,
          "refId": "A"
        }
      ],
      "title": "TCP 状态信息",
      "type": "timeseries"
    },
    {
      "datasource": {
        "type": "prometheus",
        "uid": "${DS_PROMETHEUS}"
      },
      "description": "Read bytes 每个磁盘分区每秒读取的比特数\nWritten bytes 每个磁盘分区每秒写入的比特数",
      "fieldConfig": {
        "defaults": {
          "color": {
            "mode": "palette-classic"
          },
          "custom": {
            "axisCenteredZero": false,
            "axisColorMode": "text",
            "axisLabel": "读取（-）/写入（+）",
            "axisPlacement": "auto",
            "barAlignment": 0,
            "drawStyle": "line",
            "fillOpacity": 10,
            "gradientMode": "opacity",
            "hideFrom": {
              "legend": false,
              "tooltip": false,
              "viz": false
            },
            "lineInterpolation": "linear",
            "lineWidth": 2,
            "pointSize": 5,
            "scaleDistribution": {
              "type": "linear"
            },
            "showPoints": "never",
            "spanNulls": true,
            "stacking": {
              "group": "A",
              "mode": "none"
            },
            "thresholdsStyle": {
              "mode": "off"
            }
          },
          "links": [],
          "mappings": [],
          "thresholds": {
            "mode": "absolute",
            "steps": [
              {
                "color": "green",
                "value": null
              },
              {
                "color": "red",
                "value": 80
              }
            ]
          },
          "unit": "binBps"
        },
        "overrides": [
          {
            "matcher": {
              "id": "byName",
              "options": "vda_write"
            },
            "properties": [
              {
                "id": "color",
                "value": {
                  "fixedColor": "#6ED0E0",
                  "mode": "fixed"
                }
              }
            ]
          },
          {
            "matcher": {
              "id": "byRegexp",
              "options": "/.*_读取$/"
            },
            "properties": [
              {
                "id": "custom.transform",
                "value": "negative-Y"
              }
            ]
          }
        ]
      },
      "gridPos": {
        "h": 7,
        "w": 8,
        "x": 0,
        "y": 29
      },
      "id": 168,
      "links": [],
      "options": {
        "legend": {
          "calcs": [
            "mean",
            "lastNotNull",
            "max"
          ],
          "displayMode": "table",
          "placement": "bottom",
          "showLegend": true
        },
        "tooltip": {
          "mode": "multi",
          "sort": "desc"
        }
      },
      "pluginVersion": "8.4.6",
      "targets": [
        {
          "datasource": {
            "type": "prometheus",
            "uid": "${DS_PROMETHEUS}"
          },
          "exemplar": true,
          "expr": "irate(node_disk_read_bytes_total{instance=~\"$Node_name\"}[5m])",
          "format": "time_series",
          "interval": "",
          "intervalFactor": 1,
          "legendFormat": "$host_ip-{{device}}_读取",
          "refId": "A",
          "step": 10
        },
        {
          "datasource": {
            "type": "prometheus",
            "uid": "${DS_PROMETHEUS}"
          },
          "exemplar": true,
          "expr": "irate(node_disk_written_bytes_total{instance=~\"$Node_name\"}[5m])",
          "format": "time_series",
          "hide": false,
          "interval": "",
          "intervalFactor": 1,
          "legendFormat": "$host_ip-{{device}}_写入",
          "refId": "B",
          "step": 10
        }
      ],
      "title": "每秒磁盘读写速度",
      "type": "timeseries"
    },
    {
      "aliasColors": {
        "Idle - Waiting for something to happen": "#052B51",
        "guest": "#9AC48A",
        "idle": "#052B51",
        "iowait": "#EAB839",
        "irq": "#BF1B00",
        "nice": "#C15C17",
        "sdb_每秒I/O操作%": "#d683ce",
        "softirq": "#E24D42",
        "steal": "#FCE2DE",
        "system": "#508642",
        "user": "#5195CE",
        "磁盘花费在I/O操作占比": "#ba43a9"
      },
      "bars": false,
      "dashLength": 10,
      "dashes": false,
      "datasource": {
        "type": "prometheus",
        "uid": "${DS_PROMETHEUS}"
      },
      "description": "每一秒钟的自然时间内，花费在I/O上的耗时。（wall-clock time）\n\nnode_disk_io_time_seconds_total：\n磁盘花费在输入/输出操作上的秒数。该值为累加值。（Milliseconds Spent Doing I/Os）\n\nirate(node_disk_io_time_seconds_total[1m])：\n计算每秒的速率：(last值-last前一个值)/时间戳差值，即：1秒钟内磁盘花费在I/O操作的时间占比。",
      "fieldConfig": {
        "defaults": {
          "links": []
        },
        "overrides": []
      },
      "fill": 0,
      "fillGradient": 5,
      "gridPos": {
        "h": 7,
        "w": 8,
        "x": 8,
        "y": 29
      },
      "hiddenSeries": false,
      "id": 175,
      "legend": {
        "alignAsTable": true,
        "avg": true,
        "current": true,
        "hideEmpty": true,
        "hideZero": true,
        "max": true,
        "min": false,
        "rightSide": false,
        "show": true,
        "total": false,
        "values": true
      },
      "lines": true,
      "linewidth": 2,
      "links": [],
      "maxPerRow": 6,
      "nullPointMode": "null",
      "options": {
        "alertThreshold": true
      },
      "percentage": false,
      "pluginVersion": "9.1.6",
      "pointradius": 5,
      "points": false,
      "renderer": "flot",
      "seriesOverrides": [],
      "spaceLength": 10,
      "stack": false,
      "steppedLine": false,
      "targets": [
        {
          "datasource": {
            "type": "prometheus",
            "uid": "${DS_PROMETHEUS}"
          },
          "exemplar": true,
          "expr": "irate(node_disk_io_time_seconds_total{instance=~\"$Node_name\"}[5m])",
          "format": "time_series",
          "interval": "",
          "intervalFactor": 1,
          "legendFormat": "$host_ip-{{device}}_每秒I/O操作",
          "refId": "C"
        }
      ],
      "thresholds": [],
      "timeRegions": [],
      "title": "每1秒内I/O操作耗费的时间",
      "tooltip": {
        "shared": true,
        "sort": 2,
        "value_type": "individual"
      },
      "type": "graph",
      "xaxis": {
        "mode": "time",
        "show": true,
        "values": []
      },
      "yaxes": [
        {
          "$$hashKey": "object:495",
          "format": "s",
          "label": "",
          "logBase": 1,
          "show": true
        },
        {
          "$$hashKey": "object:496",
          "format": "short",
          "logBase": 1,
          "show": false
        }
      ],
      "yaxis": {
        "align": false
      }
    },
    {
      "aliasColors": {
        "vda": "#6ED0E0"
      },
      "bars": false,
      "dashLength": 10,
      "dashes": false,
      "datasource": {
        "type": "prometheus",
        "uid": "${DS_PROMETHEUS}"
      },
      "description": "Read time seconds 每个磁盘分区读操作花费的秒数\n\nWrite time seconds 每个磁盘分区写操作花费的秒数\n\nIO time seconds 每个磁盘分区输入/输出操作花费的秒数\n\nIO time weighted seconds每个磁盘分区输入/输出操作花费的加权秒数",
      "fieldConfig": {
        "defaults": {
          "links": []
        },
        "overrides": []
      },
      "fill": 1,
      "fillGradient": 1,
      "gridPos": {
        "h": 7,
        "w": 8,
        "x": 16,
        "y": 29
      },
      "height": "300",
      "hiddenSeries": false,
      "id": 160,
      "legend": {
        "alignAsTable": true,
        "avg": true,
        "current": true,
        "hideEmpty": true,
        "hideZero": true,
        "max": true,
        "min": false,
        "show": true,
        "sort": "current",
        "sortDesc": true,
        "total": false,
        "values": true
      },
      "lines": true,
      "linewidth": 2,
      "links": [],
      "nullPointMode": "null as zero",
      "options": {
        "alertThreshold": true
      },
      "percentage": false,
      "pluginVersion": "9.1.6",
      "pointradius": 5,
      "points": false,
      "renderer": "flot",
      "seriesOverrides": [
        {
          "$$hashKey": "object:222",
          "alias": "/,*_读取$/",
          "transform": "negative-Y"
        }
      ],
      "spaceLength": 10,
      "stack": false,
      "steppedLine": false,
      "targets": [
        {
          "datasource": {
            "type": "prometheus",
            "uid": "${DS_PROMETHEUS}"
          },
          "exemplar": true,
          "expr": "irate(node_disk_read_time_seconds_total{instance=~\"$Node_name\"}[5m]) / irate(node_disk_reads_completed_total{instance=~\"$Node_name\"}[5m])",
          "format": "time_series",
          "hide": false,
          "instant": false,
          "interval": "",
          "intervalFactor": 1,
          "legendFormat": "$host_ip-{{device}}_读取",
          "refId": "B"
        },
        {
          "datasource": {
            "type": "prometheus",
            "uid": "${DS_PROMETHEUS}"
          },
          "exemplar": true,
          "expr": "irate(node_disk_write_time_seconds_total{instance=~\"$Node_name\"}[5m]) / irate(node_disk_writes_completed_total{instance=~\"$Node_name\"}[5m])",
          "format": "time_series",
          "hide": false,
          "instant": false,
          "interval": "",
          "intervalFactor": 1,
          "legendFormat": "$host_ip-{{device}}_写入",
          "refId": "C"
        },
        {
          "datasource": {
            "type": "prometheus",
            "uid": "${DS_PROMETHEUS}"
          },
          "exemplar": true,
          "expr": "irate(node_disk_io_time_seconds_total{instance=~\"$Node_name\"}[5m])",
          "format": "time_series",
          "hide": false,
          "interval": "",
          "intervalFactor": 1,
          "legendFormat": "$host_ip-{{device}}",
          "refId": "A",
          "step": 10
        },
        {
          "datasource": {
            "type": "prometheus",
            "uid": "${DS_PROMETHEUS}"
          },
          "exemplar": true,
          "expr": "irate(node_disk_io_time_weighted_seconds_total{instance=~\"$Node_name\"}[5m])",
          "format": "time_series",
          "hide": false,
          "interval": "",
          "intervalFactor": 1,
          "legendFormat": "$host_ip-{{device}}_加权",
          "refId": "D"
        }
      ],
      "thresholds": [],
      "timeRegions": [],
      "title": "每次IO读写的耗时（参考：小于100ms）(beta)",
      "tooltip": {
        "shared": true,
        "sort": 2,
        "value_type": "individual"
      },
      "type": "graph",
      "xaxis": {
        "mode": "time",
        "show": true,
        "values": []
      },
      "yaxes": [
        {
          "$$hashKey": "object:229",
          "format": "s",
          "label": "读取（-）/写入（+）",
          "logBase": 1,
          "show": true
        },
        {
          "$$hashKey": "object:230",
          "format": "short",
          "logBase": 1,
          "show": false
        }
      ],
      "yaxis": {
        "align": false
      }
    },
    {
      "collapsed": false,
      "datasource": {
        "type": "prometheus",
        "uid": "8dd2912a-9d69-4e8a-8c40-c4517dcb4e2e"
      },
      "gridPos": {
        "h": 1,
        "w": 24,
        "x": 0,
        "y": 36
      },
      "id": 225,
      "panels": [],
      "targets": [
        {
          "datasource": {
            "type": "prometheus",
            "uid": "8dd2912a-9d69-4e8a-8c40-c4517dcb4e2e"
          },
          "refId": "A"
        }
      ],
      "title": "当前节点Pod总体资源使用信息",
      "type": "row"
    },
    {
      "datasource": {
        "type": "prometheus",
        "uid": "${DS_PROMETHEUS}"
      },
      "fieldConfig": {
        "defaults": {
          "decimals": 1,
          "mappings": [],
          "max": 100,
          "min": 0,
          "thresholds": {
            "mode": "absolute",
            "steps": [
              {
                "color": "green",
                "value": null
              },
              {
                "color": "#EAB839",
                "value": 85
              },
              {
                "color": "red",
                "value": 90
              }
            ]
          },
          "unit": "percent"
        },
        "overrides": []
      },
      "gridPos": {
        "h": 8,
        "w": 12,
        "x": 0,
        "y": 37
      },
      "id": 227,
      "options": {
        "displayMode": "lcd",
        "minVizHeight": 10,
        "minVizWidth": 0,
        "orientation": "horizontal",
        "reduceOptions": {
          "calcs": [
            "mean"
          ],
          "fields": "",
          "values": false
        },
        "showUnfilled": true,
        "text": {}
      },
      "pluginVersion": "9.1.6",
      "targets": [
        {
          "datasource": {
            "type": "prometheus",
            "uid": "${DS_PROMETHEUS}"
          },
          "exemplar": true,
          "expr": "sum(kube_pod_container_resource_requests{resource=\"cpu\",job=\"kube-state-metrics\",node=~\"$Node_name\"})/sum(kube_node_status_allocatable{resource=\"cpu\",job=\"kube-state-metrics\",node=~\"$Node_name\"})*100",
          "interval": "",
          "legendFormat": "CPU Allocated By Node",
          "refId": "A"
        },
        {
          "datasource": {
            "type": "prometheus",
            "uid": "${DS_PROMETHEUS}"
          },
          "exemplar": true,
          "expr": "sum(kube_pod_container_resource_requests{resource=\"memory\",job=\"kube-state-metrics\",node=~\"$Node_name\"})/sum(kube_node_status_allocatable{resource=\"memory\",job=\"kube-state-metrics\",node=~\"$Node_name\"})*100",
          "interval": "",
          "legendFormat": "Memory Alllocated By Node",
          "refId": "B"
        }
      ],
      "title": "当前节点已分配资源（describe node）",
      "type": "bargauge"
    },
    {
      "aliasColors": {},
      "bars": false,
      "dashLength": 10,
      "dashes": false,
      "datasource": {
        "type": "prometheus",
        "uid": "${DS_PROMETHEUS}"
      },
      "fieldConfig": {
        "defaults": {
          "links": []
        },
        "overrides": []
      },
      "fill": 1,
      "fillGradient": 0,
      "gridPos": {
        "h": 8,
        "w": 12,
        "x": 12,
        "y": 37
      },
      "hiddenSeries": false,
      "id": 207,
      "legend": {
        "avg": false,
        "current": false,
        "max": false,
        "min": false,
        "show": true,
        "total": false,
        "values": false
      },
      "lines": true,
      "linewidth": 1,
      "nullPointMode": "null",
      "options": {
        "alertThreshold": true
      },
      "percentage": false,
      "pluginVersion": "9.1.6",
      "pointradius": 2,
      "points": false,
      "renderer": "flot",
      "seriesOverrides": [],
      "spaceLength": 10,
      "stack": false,
      "steppedLine": false,
      "targets": [
        {
          "datasource": {
            "type": "prometheus",
            "uid": "${DS_PROMETHEUS}"
          },
          "exemplar": true,
          "expr": "avg(sum((1 - avg(irate(node_cpu_seconds_total{mode=\"idle\",job=\"node-exporter-discovery\",instance=~\"$Node_name\"}[5m])) by (instance))*100) by (instance))",
          "interval": "",
          "legendFormat": "$host_ip",
          "refId": "A"
        }
      ],
      "thresholds": [],
      "timeRegions": [],
      "title": "当前node节点pod总体CPU使用率（kubectl top命令）",
      "tooltip": {
        "shared": true,
        "sort": 0,
        "value_type": "individual"
      },
      "type": "graph",
      "xaxis": {
        "mode": "time",
        "show": true,
        "values": []
      },
      "yaxes": [
        {
          "$$hashKey": "object:2758",
          "format": "percent",
          "logBase": 1,
          "show": true
        },
        {
          "$$hashKey": "object:2759",
          "format": "short",
          "logBase": 1,
          "show": true
        }
      ],
      "yaxis": {
        "align": false
      }
    },
    {
      "aliasColors": {},
      "bars": false,
      "dashLength": 10,
      "dashes": false,
      "datasource": {
        "type": "prometheus",
        "uid": "${DS_PROMETHEUS}"
      },
      "fieldConfig": {
        "defaults": {
          "links": []
        },
        "overrides": []
      },
      "fill": 1,
      "fillGradient": 0,
      "gridPos": {
        "h": 8,
        "w": 12,
        "x": 0,
        "y": 45
      },
      "hiddenSeries": false,
      "id": 205,
      "legend": {
        "avg": false,
        "current": false,
        "max": false,
        "min": false,
        "show": true,
        "total": false,
        "values": false
      },
      "lines": true,
      "linewidth": 1,
      "nullPointMode": "null",
      "options": {
        "alertThreshold": true
      },
      "percentage": false,
      "pluginVersion": "9.1.6",
      "pointradius": 2,
      "points": false,
      "renderer": "flot",
      "seriesOverrides": [],
      "spaceLength": 10,
      "stack": false,
      "steppedLine": false,
      "targets": [
        {
          "datasource": {
            "type": "prometheus",
            "uid": "${DS_PROMETHEUS}"
          },
          "exemplar": true,
          "expr": "sum(sum((node_memory_Active_file_bytes{job=\"node-exporter-discovery\",instance=~\"$Node_name\"}+node_memory_Active_anon_bytes{job=\"node-exporter-discovery\",instance=~\"$Node_name\"}) / node_memory_MemTotal_bytes{job=\"node-exporter-discovery\",instance=~\"$Node_name\"}) by (instance)) *100",
          "interval": "",
          "legendFormat": "$host_ip",
          "refId": "A"
        }
      ],
      "thresholds": [],
      "timeRegions": [],
      "title": "当前node节点pod总体内存使用率（kubectl top命令）",
      "tooltip": {
        "shared": true,
        "sort": 0,
        "value_type": "individual"
      },
      "type": "graph",
      "xaxis": {
        "mode": "time",
        "show": true,
        "values": []
      },
      "yaxes": [
        {
          "$$hashKey": "object:2911",
          "format": "percent",
          "logBase": 1,
          "show": true
        },
        {
          "$$hashKey": "object:2912",
          "format": "short",
          "logBase": 1,
          "show": true
        }
      ],
      "yaxis": {
        "align": false
      }
    },
    {
      "datasource": {
        "type": "prometheus",
        "uid": "${DS_PROMETHEUS}"
      },
      "fieldConfig": {
        "defaults": {
          "color": {
            "mode": "palette-classic"
          },
          "custom": {
            "axisCenteredZero": false,
            "axisColorMode": "text",
            "axisLabel": "",
            "axisPlacement": "auto",
            "barAlignment": 0,
            "drawStyle": "line",
            "fillOpacity": 10,
            "gradientMode": "none",
            "hideFrom": {
              "legend": false,
              "tooltip": false,
              "viz": false
            },
            "lineInterpolation": "linear",
            "lineWidth": 1,
            "pointSize": 5,
            "scaleDistribution": {
              "type": "linear"
            },
            "showPoints": "never",
            "spanNulls": true,
            "stacking": {
              "group": "A",
              "mode": "none"
            },
            "thresholdsStyle": {
              "mode": "off"
            }
          },
          "decimals": 1,
          "links": [],
          "mappings": [],
          "thresholds": {
            "mode": "absolute",
            "steps": [
              {
                "color": "green",
                "value": null
              },
              {
                "color": "red",
                "value": 80
              }
            ]
          },
          "unit": "gbytes"
        },
        "overrides": []
      },
      "gridPos": {
        "h": 8,
        "w": 12,
        "x": 12,
        "y": 45
      },
      "id": 209,
      "options": {
        "legend": {
          "calcs": [
            "lastNotNull"
          ],
          "displayMode": "table",
          "placement": "right",
          "showLegend": true
        },
        "tooltip": {
          "mode": "multi",
          "sort": "none"
        }
      },
      "pluginVersion": "8.4.6",
      "targets": [
        {
          "datasource": {
            "type": "prometheus",
            "uid": "${DS_PROMETHEUS}"
          },
          "exemplar": true,
          "expr": "sum(kube_node_status_capacity{resource=\"memory\",job=\"kube-state-metrics\",node=~\"$Node_name\"}/1024/1024/1024)",
          "interval": "",
          "legendFormat": "Total",
          "refId": "A"
        },
        {
          "datasource": {
            "type": "prometheus",
            "uid": "${DS_PROMETHEUS}"
          },
          "exemplar": true,
          "expr": "sum(kube_pod_container_resource_requests{resource=\"memory\",job=\"kube-state-metrics\",node=~\"$Node_name\"}/1024/1024/1024)",
          "interval": "",
          "legendFormat": "Requests",
          "refId": "B"
        },
        {
          "datasource": {
            "type": "prometheus",
            "uid": "${DS_PROMETHEUS}"
          },
          "exemplar": true,
          "expr": "sum(kube_pod_container_resource_limits{resource=\"memory\",job=\"kube-state-metrics\",node=~\"$Node_name\"}/1024/1024/1024)",
          "interval": "",
          "legendFormat": "Limits",
          "refId": "C"
        }
      ],
      "title": "Pod 总体Mem资源申请情况",
      "type": "timeseries"
    },
    {
      "datasource": {
        "type": "prometheus",
        "uid": "${DS_PROMETHEUS}"
      },
      "fieldConfig": {
        "defaults": {
          "color": {
            "mode": "palette-classic"
          },
          "custom": {
            "axisCenteredZero": false,
            "axisColorMode": "text",
            "axisLabel": "",
            "axisPlacement": "auto",
            "barAlignment": 0,
            "drawStyle": "line",
            "fillOpacity": 10,
            "gradientMode": "none",
            "hideFrom": {
              "legend": false,
              "tooltip": false,
              "viz": false
            },
            "lineInterpolation": "linear",
            "lineWidth": 1,
            "pointSize": 5,
            "scaleDistribution": {
              "type": "linear"
            },
            "showPoints": "never",
            "spanNulls": true,
            "stacking": {
              "group": "A",
              "mode": "none"
            },
            "thresholdsStyle": {
              "mode": "off"
            }
          },
          "links": [],
          "mappings": [],
          "thresholds": {
            "mode": "absolute",
            "steps": [
              {
                "color": "green",
                "value": null
              },
              {
                "color": "red",
                "value": 80
              }
            ]
          },
          "unit": "Bps"
        },
        "overrides": []
      },
      "gridPos": {
        "h": 8,
        "w": 24,
        "x": 0,
        "y": 53
      },
      "id": 223,
      "options": {
        "legend": {
          "calcs": [
            "lastNotNull",
            "max"
          ],
          "displayMode": "table",
          "placement": "right",
          "showLegend": true
        },
        "tooltip": {
          "mode": "multi",
          "sort": "none"
        }
      },
      "pluginVersion": "8.4.6",
      "targets": [
        {
          "datasource": {
            "type": "prometheus",
            "uid": "${DS_PROMETHEUS}"
          },
          "exemplar": true,
          "expr": "avg(irate(container_network_receive_bytes_total{instance=~\"$host_ip:10250\",pod!=\"\"}[2m])) by (pod)",
          "interval": "",
          "legendFormat": "{{pod}}",
          "refId": "A"
        }
      ],
      "title": "当前节点所有pod网络入流量",
      "type": "timeseries"
    },
    {
      "datasource": {
        "type": "prometheus",
        "uid": "${DS_PROMETHEUS}"
      },
      "fieldConfig": {
        "defaults": {
          "color": {
            "mode": "palette-classic"
          },
          "custom": {
            "axisCenteredZero": false,
            "axisColorMode": "text",
            "axisLabel": "",
            "axisPlacement": "auto",
            "barAlignment": 0,
            "drawStyle": "line",
            "fillOpacity": 10,
            "gradientMode": "none",
            "hideFrom": {
              "legend": false,
              "tooltip": false,
              "viz": false
            },
            "lineInterpolation": "linear",
            "lineWidth": 1,
            "pointSize": 5,
            "scaleDistribution": {
              "type": "linear"
            },
            "showPoints": "never",
            "spanNulls": true,
            "stacking": {
              "group": "A",
              "mode": "none"
            },
            "thresholdsStyle": {
              "mode": "off"
            }
          },
          "links": [],
          "mappings": [],
          "thresholds": {
            "mode": "absolute",
            "steps": [
              {
                "color": "green",
                "value": null
              },
              {
                "color": "red",
                "value": 80
              }
            ]
          },
          "unit": "Bps"
        },
        "overrides": []
      },
      "gridPos": {
        "h": 8,
        "w": 24,
        "x": 0,
        "y": 61
      },
      "id": 221,
      "options": {
        "legend": {
          "calcs": [
            "lastNotNull",
            "max"
          ],
          "displayMode": "table",
          "placement": "right",
          "showLegend": true
        },
        "tooltip": {
          "mode": "multi",
          "sort": "none"
        }
      },
      "pluginVersion": "8.4.6",
      "targets": [
        {
          "datasource": {
            "type": "prometheus",
            "uid": "${DS_PROMETHEUS}"
          },
          "exemplar": true,
          "expr": "avg(irate(container_network_transmit_bytes_total{instance=~\"$host_ip:10250\",pod!=\"\"}[2m]))by (pod)",
          "interval": "",
          "legendFormat": "{{pod}}",
          "refId": "A"
        }
      ],
      "title": "当前节点所有pod网络出流量",
      "type": "timeseries"
    },
    {
      "datasource": {
        "type": "prometheus",
        "uid": "${DS_PROMETHEUS}"
      },
      "fieldConfig": {
        "defaults": {
          "color": {
            "mode": "palette-classic"
          },
          "custom": {
            "axisCenteredZero": false,
            "axisColorMode": "text",
            "axisLabel": "",
            "axisPlacement": "auto",
            "barAlignment": 0,
            "drawStyle": "line",
            "fillOpacity": 10,
            "gradientMode": "none",
            "hideFrom": {
              "legend": false,
              "tooltip": false,
              "viz": false
            },
            "lineInterpolation": "linear",
            "lineWidth": 1,
            "pointSize": 5,
            "scaleDistribution": {
              "type": "linear"
            },
            "showPoints": "never",
            "spanNulls": true,
            "stacking": {
              "group": "A",
              "mode": "none"
            },
            "thresholdsStyle": {
              "mode": "off"
            }
          },
          "decimals": 0,
          "links": [],
          "mappings": [],
          "thresholds": {
            "mode": "absolute",
            "steps": [
              {
                "color": "green",
                "value": null
              },
              {
                "color": "red",
                "value": 80
              }
            ]
          },
          "unit": "percent"
        },
        "overrides": []
      },
      "gridPos": {
        "h": 8,
        "w": 24,
        "x": 0,
        "y": 69
      },
      "id": 197,
      "options": {
        "legend": {
          "calcs": [
            "lastNotNull",
            "max",
            "min"
          ],
          "displayMode": "table",
          "placement": "right",
          "showLegend": true
        },
        "tooltip": {
          "mode": "multi",
          "sort": "none"
        }
      },
      "pluginVersion": "8.4.6",
      "targets": [
        {
          "datasource": {
            "type": "prometheus",
            "uid": "${DS_PROMETHEUS}"
          },
          "editorMode": "code",
          "exemplar": true,
          "expr": "avg(sum(container_memory_working_set_bytes{container!=\"\",container!=\"POD\",instance=~\"$host_ip:10250\"}) by (service,pod)) by (pod)/avg(sum(kube_pod_container_resource_limits{container!=\"\",container!=\"POD\",node=\"$Node_name\"}>0) by (service,pod)) by (pod) * 100",
          "interval": "",
          "legendFormat": "{{pod}}",
          "range": true,
          "refId": "B"
        }
      ],
      "title": "当前node节点所有pod 内存使用率（current/limits）",
      "type": "timeseries"
    },
    {
      "datasource": {
        "type": "prometheus",
        "uid": "${DS_PROMETHEUS}"
      },
      "fieldConfig": {
        "defaults": {
          "color": {
            "mode": "palette-classic"
          },
          "custom": {
            "axisCenteredZero": false,
            "axisColorMode": "text",
            "axisLabel": "",
            "axisPlacement": "auto",
            "barAlignment": 0,
            "drawStyle": "line",
            "fillOpacity": 6,
            "gradientMode": "none",
            "hideFrom": {
              "legend": false,
              "tooltip": false,
              "viz": false
            },
            "lineInterpolation": "linear",
            "lineStyle": {
              "fill": "solid"
            },
            "lineWidth": 1,
            "pointSize": 2,
            "scaleDistribution": {
              "type": "linear"
            },
            "showPoints": "never",
            "spanNulls": false,
            "stacking": {
              "group": "A",
              "mode": "normal"
            },
            "thresholdsStyle": {
              "mode": "off"
            }
          },
          "decimals": 1,
          "links": [],
          "mappings": [],
          "thresholds": {
            "mode": "absolute",
            "steps": [
              {
                "color": "green",
                "value": null
              },
              {
                "color": "red",
                "value": 80
              }
            ]
          },
          "unit": "bytes"
        },
        "overrides": []
      },
      "gridPos": {
        "h": 8,
        "w": 24,
        "x": 0,
        "y": 77
      },
      "id": 228,
      "options": {
        "legend": {
          "calcs": [
            "lastNotNull",
            "max"
          ],
          "displayMode": "table",
          "placement": "right",
          "showLegend": true,
          "sortBy": "Max",
          "sortDesc": false
        },
        "tooltip": {
          "mode": "multi",
          "sort": "none"
        }
      },
      "pluginVersion": "8.4.6",
      "targets": [
        {
          "datasource": {
            "type": "prometheus",
            "uid": "${DS_PROMETHEUS}"
          },
          "editorMode": "code",
          "exemplar": true,
          "expr": "avg(sum(container_memory_working_set_bytes{container!=\"\",container!=\"POD\",instance=~\"$host_ip:10250\"}) by (service,pod)) by (pod)/avg(sum(container_spec_memory_limit_bytes{container!=\"\",container!=\"POD\",instance=~\"$host_ip:10250\"}) by (service,pod)) by (pod) * 100",
          "hide": true,
          "interval": "",
          "legendFormat": "{{pod}}",
          "range": true,
          "refId": "B"
        },
        {
          "datasource": {
            "type": "prometheus",
            "uid": "${DS_PROMETHEUS}"
          },
          "exemplar": true,
          "expr": "avg by (namespace,pod) (container_memory_usage_bytes{instance=~\"$host_ip:10250\",container!=\"\"})",
          "hide": false,
          "interval": "",
          "legendFormat": "{{pod}}",
          "refId": "A"
        }
      ],
      "title": "当前node节点所有pod 内存使用量",
      "type": "timeseries"
    },
    {
      "datasource": {
        "type": "prometheus",
        "uid": "${DS_PROMETHEUS}"
      },
      "fieldConfig": {
        "defaults": {
          "color": {
            "mode": "palette-classic"
          },
          "custom": {
            "axisCenteredZero": false,
            "axisColorMode": "text",
            "axisLabel": "",
            "axisPlacement": "auto",
            "barAlignment": 0,
            "drawStyle": "line",
            "fillOpacity": 8,
            "gradientMode": "none",
            "hideFrom": {
              "legend": false,
              "tooltip": false,
              "viz": false
            },
            "lineInterpolation": "linear",
            "lineWidth": 1,
            "pointSize": 5,
            "scaleDistribution": {
              "type": "linear"
            },
            "showPoints": "never",
            "spanNulls": true,
            "stacking": {
              "group": "A",
              "mode": "none"
            },
            "thresholdsStyle": {
              "mode": "off"
            }
          },
          "decimals": 1,
          "links": [],
          "mappings": [],
          "thresholds": {
            "mode": "absolute",
            "steps": [
              {
                "color": "green",
                "value": null
              },
              {
                "color": "red",
                "value": 80
              }
            ]
          },
          "unit": "percent"
        },
        "overrides": []
      },
      "gridPos": {
        "h": 8,
        "w": 24,
        "x": 0,
        "y": 85
      },
      "id": 199,
      "options": {
        "legend": {
          "calcs": [
            "lastNotNull",
            "max",
            "min"
          ],
          "displayMode": "table",
          "placement": "right",
          "showLegend": true
        },
        "tooltip": {
          "mode": "multi",
          "sort": "none"
        }
      },
      "pluginVersion": "8.4.6",
      "targets": [
        {
          "datasource": {
            "type": "prometheus",
            "uid": "${DS_PROMETHEUS}"
          },
          "editorMode": "code",
          "exemplar": true,
          "expr": "sum(avg(irate(container_cpu_usage_seconds_total{container !=\"\",container!=\"POD\",instance=~\"$host_ip:10250\"}[2m])) by(container,pod)) by (pod)/sum(avg(kube_pod_container_resource_limits{container !=\"\",container!=\"POD\",resource=\"cpu\"}) by (container,pod)) by (pod)*100",
          "hide": false,
          "interval": "",
          "legendFormat": "{{pod}}",
          "range": true,
          "refId": "B"
        }
      ],
      "title": "当前node节点所有Pod CPU使用率(current/limits)",
      "type": "timeseries"
    }
  ],
  "refresh": "5m",
  "schemaVersion": 37,
  "style": "dark",
  "tags": [
    "Prometheus",
    "node_exporter",
    "StarsL.cn"
  ],
  "templating": {
    "list": [
      {
        "current": {
          "selected": true,
          "text": "prometheus",
          "value": "prometheus"
        },
        "hide": 0,
        "includeAll": false,
        "label": "Datasource",
        "multi": false,
        "name": "DS_PROMETHEUS",
        "options": [],
        "query": "prometheus",
        "queryValue": "",
        "refresh": 1,
        "regex": "",
        "skipUrlSync": false,
        "type": "datasource"
      },
      {
        "current": {},
        "datasource": {
          "type": "prometheus",
          "uid": "${DS_PROMETHEUS}"
        },
        "definition": "label_values(node_load1{job=\"node-exporter-discovery\"},instance)",
        "hide": 0,
        "includeAll": false,
        "label": "Node_name",
        "multi": false,
        "name": "Node_name",
        "options": [],
        "query": {
          "query": "label_values(node_load1{job=\"node-exporter-discovery\"},instance)",
          "refId": "StandardVariableQuery"
        },
        "refresh": 1,
        "regex": "",
        "skipUrlSync": false,
        "sort": 5,
        "tagValuesQuery": "",
        "tagsQuery": "",
        "type": "query",
        "useTags": false
      },
      {
        "current": {},
        "datasource": {
          "type": "prometheus",
          "uid": "${DS_PROMETHEUS}"
        },
        "definition": "label_values(node_load1{job=\"node-exporter-discovery\", instance =~\"$Node_name\"}, host_ip)",
        "hide": 0,
        "includeAll": false,
        "label": "host_ip",
        "multi": false,
        "name": "host_ip",
        "options": [],
        "query": {
          "query": "label_values(node_load1{job=\"node-exporter-discovery\", instance =~\"$Node_name\"}, host_ip)",
          "refId": "StandardVariableQuery"
        },
        "refresh": 1,
        "regex": "",
        "skipUrlSync": false,
        "sort": 5,
        "tagValuesQuery": "",
        "tagsQuery": "",
        "type": "query",
        "useTags": false
      },
      {
        "current": {},
        "datasource": {
          "type": "prometheus",
          "uid": "${DS_PROMETHEUS}"
        },
        "definition": "label_values(kube_pod_info{node =~\"$Node_name\"},namespace)",
        "hide": 0,
        "includeAll": false,
        "label": "namespace",
        "multi": false,
        "name": "NameSpace",
        "options": [],
        "query": {
          "query": "label_values(kube_pod_info{node =~\"$Node_name\"},namespace)",
          "refId": "StandardVariableQuery"
        },
        "refresh": 1,
        "regex": "",
        "skipUrlSync": false,
        "sort": 5,
        "tagValuesQuery": "",
        "tagsQuery": "",
        "type": "query",
        "useTags": false
      },
      {
        "current": {},
        "datasource": {
          "type": "prometheus",
          "uid": "${DS_PROMETHEUS}"
        },
        "definition": "label_values(kube_pod_info{node =~\"$Node_name\",namespace=~\"$NameSpace\"},pod)",
        "hide": 0,
        "includeAll": false,
        "label": "Pod",
        "multi": false,
        "name": "Pod",
        "options": [],
        "query": {
          "query": "label_values(kube_pod_info{node =~\"$Node_name\",namespace=~\"$NameSpace\"},pod)",
          "refId": "StandardVariableQuery"
        },
        "refresh": 1,
        "regex": "",
        "skipUrlSync": false,
        "sort": 0,
        "tagValuesQuery": "",
        "tagsQuery": "",
        "type": "query",
        "useTags": false
      },
      {
        "current": {},
        "datasource": {
          "type": "prometheus",
          "uid": "${DS_PROMETHEUS}"
        },
        "definition": "label_values(kube_pod_container_info{namespace=~\"$NameSpace\",pod=~\"$Pod\"},container)",
        "hide": 0,
        "includeAll": false,
        "label": "",
        "multi": false,
        "name": "Container",
        "options": [],
        "query": {
          "query": "label_values(kube_pod_container_info{namespace=~\"$NameSpace\",pod=~\"$Pod\"},container)",
          "refId": "StandardVariableQuery"
        },
        "refresh": 1,
        "regex": "",
        "skipUrlSync": false,
        "sort": 0,
        "tagValuesQuery": "",
        "tagsQuery": "",
        "type": "query",
        "useTags": false
      }
    ]
  },
  "time": {
    "from": "now-15m",
    "to": "now"
  },
  "timepicker": {
    "now": true,
    "refresh_intervals": [
      "10s",
      "30s",
      "1m",
      "5m",
      "15m",
      "30m",
      "1h",
      "2h",
      "1d"
    ],
    "time_options": [
      "5m",
      "15m",
      "1h",
      "6h",
      "12h",
      "24h",
      "2d",
      "7d",
      "30d"
    ]
  },
  "timezone": "browser",
  "title": "节点监控信息",
  "uid": "C2RjsIXMk",
  "version": 30,
  "weekStart": ""
}
